odoo/addons/auth_jwt/README.rst
odoo/addons/auth_jwt/__init__.py
odoo/addons/auth_jwt/__manifest__.py
odoo/addons/auth_jwt/exceptions.py
odoo/addons/auth_jwt/i18n/auth_jwt.pot
odoo/addons/auth_jwt/i18n/it.po
odoo/addons/auth_jwt/models/__init__.py
odoo/addons/auth_jwt/models/auth_jwt_validator.py
odoo/addons/auth_jwt/models/ir_http.py
odoo/addons/auth_jwt/readme/CONTRIBUTORS.rst
odoo/addons/auth_jwt/readme/DESCRIPTION.rst
odoo/addons/auth_jwt/readme/INSTALL.rst
odoo/addons/auth_jwt/readme/USAGE.rst
odoo/addons/auth_jwt/security/ir.model.access.csv
odoo/addons/auth_jwt/static/description/icon.png
odoo/addons/auth_jwt/static/description/index.html
odoo/addons/auth_jwt/tests/__init__.py
odoo/addons/auth_jwt/tests/test_auth_jwt.py
odoo/addons/auth_jwt/views/auth_jwt_validator_views.xml
odoo14_addon_auth_jwt-14.0.2.1.2.dist-info/METADATA
odoo14_addon_auth_jwt-14.0.2.1.2.dist-info/WHEEL
odoo14_addon_auth_jwt-14.0.2.1.2.dist-info/top_level.txt
odoo14_addon_auth_jwt-14.0.2.1.2.dist-info/RECORD
